castep_linter/__about__.py
castep_linter/__init__.py
castep_linter/scan_files.py
castep_linter/error_logging/__init__.py
castep_linter/error_logging/error_types.py
castep_linter/error_logging/json_writer.py
castep_linter/error_logging/logger.py
castep_linter/error_logging/xml_writer.py
castep_linter/fortran/__init__.py
castep_linter/fortran/fortran_raw_types.py
castep_linter/fortran/identifier.py
castep_linter/fortran/node_factory.py
castep_linter/fortran/node_type_err.py
castep_linter/fortran/parser.py
castep_linter/fortran/fortran_nodes/__init__.py
castep_linter/fortran/fortran_nodes/argument_types.py
castep_linter/fortran/fortran_nodes/fortran_argument_list.py
castep_linter/fortran/fortran_nodes/fortran_call_expression_node.py
castep_linter/fortran/fortran_nodes/fortran_function_node.py
castep_linter/fortran/fortran_nodes/fortran_node.py
castep_linter/fortran/fortran_nodes/fortran_subroutine_node.py
castep_linter/fortran/fortran_nodes/fortran_var_decl_node.py
castep_linter/tests/__init__.py
castep_linter/tests/allocate_stat_checked.py
castep_linter/tests/castep_identifiers.py
castep_linter/tests/complex_has_dp.py
castep_linter/tests/has_trace_entry_exit.py
castep_linter/tests/number_literal_correct_kind.py
castep_linter/tests/real_declaration_has_dp.py
castep_linter-0.7.1.dist-info/METADATA
castep_linter-0.7.1.dist-info/WHEEL
castep_linter-0.7.1.dist-info/entry_points.txt
castep_linter-0.7.1.dist-info/licenses/LICENSE.txt
castep_linter-0.7.1.dist-info/RECORD
