Metadata-Version: 2.3
Name: castep-linter
Version: 0.7.1
Project-URL: Documentation, https://github.com/byornski/castep-linter#readme
Project-URL: Issues, https://github.com/byornski/castep-linter/issues
Project-URL: Source, https://github.com/byornski/castep-linter
Author-email: Peter Byrne <peter.byrne@york.ac.uk>
License-Expression: MIT
License-File: LICENSE.txt
Classifier: Development Status :: 4 - Beta
Classifier: Programming Language :: Python
Classifier: Programming Language :: Python :: 3.7
Classifier: Programming Language :: Python :: 3.8
Classifier: Programming Language :: Python :: 3.9
Classifier: Programming Language :: Python :: 3.10
Classifier: Programming Language :: Python :: 3.11
Classifier: Programming Language :: Python :: Implementation :: CPython
Classifier: Programming Language :: Python :: Implementation :: PyPy
Requires-Python: >=3.7
Requires-Dist: junitparser
Requires-Dist: rich
Requires-Dist: tree-sitter-fortran==0.0.1
Requires-Dist: tree-sitter==0.23.1
